Metadata-Version: 1.1
Name: strain3D
Version: 1.0.5
Summary: LV myocardium 3D strain from BSF model
Home-page: https://github.com/JorryZ/strain3D
Author: Yu Zheng
Author-email: jorry.zhengyu@gmail.com
License: MIT
Download-URL: https://github.com/JorryZ/strain3D/archive/v1.0.5.tar.gz
Keywords: BSF model,motion,3D strain,myocardium,ECHO
Platform: UNKNOWN
Classifier: Development Status :: 5 - Production/Stable
Classifier: Intended Audience :: Developers
Classifier: Topic :: Software Development :: Build Tools
Classifier: License :: OSI Approved :: MIT License
Classifier: Programming Language :: Python :: 3.6
Classifier: Programming Language :: Python :: 3.7
